.DS_Store
riskybusiness/__init__.py
riskybusiness-0.0.3.dist-info/LICENSE
riskybusiness-0.0.3.dist-info/METADATA
riskybusiness-0.0.3.dist-info/WHEEL
riskybusiness-0.0.3.dist-info/top_level.txt
riskybusiness-0.0.3.dist-info/RECORD
