Metadata-Version: 2.1
Name: riskybusiness
Version: 0.0.3
Summary: A Python Library containing various functions to analyse the risk of a business.
Home-page: https://rajathkotyal.github.io
Author: Rajath Kotyal
Author-email: rajathkotyal@gmail.com
License: UNKNOWN
Platform: UNKNOWN
Classifier: Programming Language :: Python :: 3
Classifier: License :: OSI Approved :: MIT License
Classifier: Operating System :: OS Independent
Requires-Python: >=3.6
Requires-Dist: pandas
Requires-Dist: numpy (>=1.14.5)
Requires-Dist: matplotlib (>=2.2.0)
Requires-Dist: scipy
